sim/RAM/sync_ram.v
module sync_ram #(
    parameter ADDR_WIDTH = 12,    // 地址宽度
    parameter DATA_WIDTH = 64,    // 数据宽度
    parameter DEPTH = 256,        // RAM深度
    parameter LOAD_FILE_PATH = "F:/project/Frodo/sim/RAM/data/B.hex", // 文件路径，默认为B.hex
    parameter STORE_FILE_PATH = "ram.txt",
    parameter TIME  = 1000
)(
    input wire clk,               // 时钟信号
    input wire rstn,              // 复位信号（低有效）
    input wire wr_en,             // 写使能
    input wire rd_en,             // 读使能
    input wire [ADDR_WIDTH-1:0] addr,  // 地址输入
    input wire [DATA_WIDTH-1:0] din,   // 数据输入
    output reg [DATA_WIDTH-1:0] dout   // 数据输出
);

    // RAM存储数组
    reg [DATA_WIDTH-1:0] ram [0:DEPTH-1];

    // 通过initial块加载HEX文件中的初始数据
    initial begin
        $readmemh(LOAD_FILE_PATH, ram);  // 从给定的路径加载数据到RAM
    end

    // 同步读操作
    always @(posedge clk or negedge rstn) begin
        if (!rstn) begin
            dout <= 0;  // 复位时，数据输出为0
        end
        else if (rd_en) begin
            dout <= ram[addr];  // 读取数据
        end
    end

    // 同步写操作
    always @(posedge clk) begin
        if (wr_en) begin
            ram[addr] <= din;  // 写入数据
        end
    end

    integer ram_file;
    integer i;

    initial begin
        // 打开文件进行写操作
        ram_file = $fopen(STORE_FILE_PATH, "w");
        // 等待仿真完成后将RAM数据写入文件
        #TIME;  // 假设仿真运行10000个时钟周期
        for (i = 0; i < DEPTH; i = i + 1) begin
            // 将每个RAM单元的数据输出到文件
            $fwrite(ram_file, "%h\n", ram[i]);
        end
        // 关闭文件
        $fclose(ram_file);
    end



endmodule

sim/RAM/tb_sync_ram.v
`timescale 1ps/1ps
`include "../RAM/sync_ram.v"
module tb_sync_ram;

    // sync_ram Parameters
    parameter PERIOD      = 10     ;
    parameter ADDR_WIDTH  = 12     ;
    parameter DATA_WIDTH  = 64     ;
    parameter DEPTH       = 1024    ;
    parameter FILE_PATH   = "F:/project/Frodo/sim/RAM/data/A.hex";

    // sync_ram Inputs
    reg   clk                                  = 0 ;
    reg   rstn                                 = 0 ;
    reg   wr_en                                = 0 ;
    reg   rd_en                                = 0 ;
    reg   [ADDR_WIDTH-1:0]  addr               = 0 ;
    reg   [DATA_WIDTH-1:0]  din                = 0 ;

    // sync_ram Outputs
    wire  [DATA_WIDTH-1:0]  dout               ;
    wire [15:0] data_0,data_1,data_2,data_3;
    assign data_0 = dout[15:0];
    assign data_1 = dout[31:16];
    assign data_2 = dout[47:32];
    assign data_3 = dout[63:48];
    
    always @(posedge clk or negedge rstn) begin
        if(!rstn)
            addr <= 12'b0;
        else begin
            if(rd_en)
                addr <= addr + 12'b1;
        end
    end


    initial
    begin
        forever #(PERIOD/2)  clk=~clk;
    end

    initial
    begin
        #(PERIOD*2) rstn  =  1;
    end

    sync_ram #(
        .ADDR_WIDTH ( ADDR_WIDTH ),
        .DATA_WIDTH ( DATA_WIDTH ),
        .DEPTH      ( DEPTH      ))
    u_sync_ram (
        .clk                     ( clk                     ),
        .rstn                    ( rstn                    ),
        .wr_en                   ( wr_en                   ),
        .rd_en                   ( rd_en                   ),
        .addr                    ( addr    ),
        .din                     ( din     ),

        .dout                    ( dout    )
    );

    initial
    begin
        $dumpfile("ram.vcd");
        $dumpvars(0,tb_sync_ram);
        clk=1;
        rstn=0;
        #40;
        rd_en = 1;
        #1000;
        $finish;
    end

endmodule

sim/RAM/ram.vcd
$date
	Fri Dec 13 17:55:28 2024
$end
$version
	Icarus Verilog
$end
$timescale
	1ps
$end
$scope module tb_sync_ram $end
$var wire 64 ! dout [63:0] $end
$var wire 16 " data_3 [15:0] $end
$var wire 16 # data_2 [15:0] $end
$var wire 16 $ data_1 [15:0] $end
$var wire 16 % data_0 [15:0] $end
$var parameter 32 & ADDR_WIDTH $end
$var parameter 32 ' DATA_WIDTH $end
$var parameter 32 ( DEPTH $end
$var parameter 280 ) FILE_PATH $end
$var parameter 32 * PERIOD $end
$var reg 12 + addr [11:0] $end
$var reg 1 , clk $end
$var reg 64 - din [63:0] $end
$var reg 1 . rd_en $end
$var reg 1 / rstn $end
$var reg 1 0 wr_en $end
$scope module u_sync_ram $end
$var wire 12 1 addr [11:0] $end
$var wire 1 , clk $end
$var wire 64 2 din [63:0] $end
$var wire 1 . rd_en $end
$var wire 1 / rstn $end
$var wire 1 0 wr_en $end
$var parameter 32 3 ADDR_WIDTH $end
$var parameter 32 4 DATA_WIDTH $end
$var parameter 32 5 DEPTH $end
$var parameter 280 6 LOAD_FILE_PATH $end
$var parameter 56 7 STORE_FILE_PATH $end
$var parameter 32 8 TIME $end
$var reg 64 9 dout [63:0] $end
$var integer 32 : i [31:0] $end
$var integer 32 ; ram_file [31:0] $end
$upscope $end
$upscope $end
$enddefinitions $end
$comment Show the parameter values. $end
$dumpall
b1111101000 8
b1110010011000010110110100101110011101000111100001110100 7
b100011000111010001011110111000001110010011011110110101001100101011000110111010000101111010001100111001001101111011001000110111100101111011100110110100101101101001011110101001001000001010011010010111101100100011000010111010001100001001011110100001000101110011010000110010101111000 6
b10000000000 5
b1000000 4
b1100 3
b1010 *
b100011000111010001011110111000001110010011011110110101001100101011000110111010000101111010001100111001001101111011001000110111100101111011100110110100101101101001011110101001001000001010011010010111101100100011000010111010001100001001011110100000100101110011010000110010101111000 )
b10000000000 (
b1000000 '
b1100 &
$end
#0
$dumpvars
b10000000000000000000000000000011 ;
bx :
b0 9
b0 2
b0 1
00
0/
0.
b0 -
1,
b0 +
b0 %
b0 $
b0 #
b0 "
b0 !
$end
#5
0,
#10
1,
#15
0,
#20
1,
1/
#25
0,
#30
1,
#35
0,
#40
b111101100101001 "
b1110010010011011 #
b110111110001 $
b1011000010011010 %
b1 +
b1 1
b111101100101001111001001001101100001101111100011011000010011010 !
b111101100101001111001001001101100001101111100011011000010011010 9
1,
1.
#45
0,
#50
b1000100100101110 "
b100011111111110 #
b1011001000110011 $
b1000010010011001 %
b1000100100101110010001111111111010110010001100111000010010011001 !
b1000100100101110010001111111111010110010001100111000010010011001 9
b10 +
b10 1
1,
#55
0,
#60
b1100101010010100 "
b101011101100110 #
b11001101000001 $
b1101111000101000 %
b11 +
b11 1
b1100101010010100010101110110011000110011010000011101111000101000 !
b1100101010010100010101110110011000110011010000011101111000101000 9
1,
#65
0,
#70
b1011010001101000 "
b1111010110001111 #
b1110101100101100 $
b10011001111100 %
b1011010001101000111101011000111111101011001011000010011001111100 !
b1011010001101000111101011000111111101011001011000010011001111100 9
b100 +
b100 1
1,
#75
0,
#80
b1101111010001101 "
b1000101011111 #
b1001011000001011 $
b1011100101100111 %
b101 +
b101 1
b1101111010001101000100010101111110010110000010111011100101100111 !
b1101111010001101000100010101111110010110000010111011100101100111 9
1,
#85
0,
#90
b101101011000111 "
b11000101101000 #
b1100011011001011 $
b1011001001000110 %
b101101011000111001100010110100011000110110010111011001001000110 !
b101101011000111001100010110100011000110110010111011001001000110 9
b110 +
b110 1
1,
#95
0,
#100
b10001110100001 "
b1100110001000001 #
b111111111111 $
b1001000000001001 %
b111 +
b111 1
b10001110100001110011000100000100001111111111111001000000001001 !
b10001110100001110011000100000100001111111111111001000000001001 9
1,
#105
0,
#110
b1111100101010001 "
b1000110010101010 #
b1110010010111 $
b1001100110111110 %
b1111100101010001100011001010101000011100100101111001100110111110 !
b1111100101010001100011001010101000011100100101111001100110111110 9
b1000 +
b1000 1
1,
#115
0,
#120
b1001100011001010 "
b1101000000001111 #
b1001111111101110 $
b101110011010011 %
b1001 +
b1001 1
b1001100011001010110100000000111110011111111011100101110011010011 !
b1001100011001010110100000000111110011111111011100101110011010011 9
1,
#125
0,
#130
b1110010001001100 "
b101001001000000 #
b1111000001010111 $
b11010001000011 %
b1110010001001100010100100100000011110000010101110011010001000011 !
b1110010001001100010100100100000011110000010101110011010001000011 9
b1010 +
b1010 1
1,
#135
0,
#140
b1110000010001111 "
b1111011110111110 #
b1110011001011110 $
b1011101100110 %
b1011 +
b1011 1
b1110000010001111111101111011111011100110010111100001011101100110 !
b1110000010001111111101111011111011100110010111100001011101100110 9
1,
#145
0,
#150
b1000010110110101 "
b111100110010001 #
b100100111000100 $
b1010001100001100 %
b1000010110110101011110011001000101001001110001001010001100001100 !
b1000010110110101011110011001000101001001110001001010001100001100 9
b1100 +
b1100 1
1,
#155
0,
#160
b11000000010111 "
b1010011000001001 #
b1001000000001100 $
b1100110010101101 %
b1101 +
b1101 1
b11000000010111101001100000100110010000000011001100110010101101 !
b11000000010111101001100000100110010000000011001100110010101101 9
1,
#165
0,
#170
b100111100001111 "
b101000001010000 #
b1001010100110101 $
b1010111001100001 %
b100111100001111010100000101000010010101001101011010111001100001 !
b100111100001111010100000101000010010101001101011010111001100001 9
b1110 +
b1110 1
1,
#175
0,
#180
b1100010100001010 "
b110000101100010 #
b1011100001001111 $
b101010101010001 %
b1111 +
b1111 1
b1100010100001010011000010110001010111000010011110101010101010001 !
b1100010100001010011000010110001010111000010011110101010101010001 9
1,
#185
0,
#190
b101101000100011 "
b10111000111000 #
b101010000111010 $
b101011101100110 %
b101101000100011001011100011100001010100001110100101011101100110 !
b101101000100011001011100011100001010100001110100101011101100110 9
b10000 +
b10000 1
1,
#195
0,
#200
bx "
bx #
bx $
bx %
b10001 +
b10001 1
bx !
bx 9
1,
#205
0,
#210
b10010 +
b10010 1
1,
#215
0,
#220
b10011 +
b10011 1
1,
#225
0,
#230
b10100 +
b10100 1
1,
#235
0,
#240
b10101 +
b10101 1
1,
#245
0,
#250
b10110 +
b10110 1
1,
#255
0,
#260
b10111 +
b10111 1
1,
#265
0,
#270
b11000 +
b11000 1
1,
#275
0,
#280
b11001 +
b11001 1
1,
#285
0,
#290
b11010 +
b11010 1
1,
#295
0,
#300
b11011 +
b11011 1
1,
#305
0,
#310
b11100 +
b11100 1
1,
#315
0,
#320
b11101 +
b11101 1
1,
#325
0,
#330
b11110 +
b11110 1
1,
#335
0,
#340
b11111 +
b11111 1
1,
#345
0,
#350
b100000 +
b100000 1
1,
#355
0,
#360
b100001 +
b100001 1
1,
#365
0,
#370
b100010 +
b100010 1
1,
#375
0,
#380
b100011 +
b100011 1
1,
#385
0,
#390
b100100 +
b100100 1
1,
#395
0,
#400
b100101 +
b100101 1
1,
#405
0,
#410
b100110 +
b100110 1
1,
#415
0,
#420
b100111 +
b100111 1
1,
#425
0,
#430
b101000 +
b101000 1
1,
#435
0,
#440
b101001 +
b101001 1
1,
#445
0,
#450
b101010 +
b101010 1
1,
#455
0,
#460
b101011 +
b101011 1
1,
#465
0,
#470
b101100 +
b101100 1
1,
#475
0,
#480
b101101 +
b101101 1
1,
#485
0,
#490
b101110 +
b101110 1
1,
#495
0,
#500
b101111 +
b101111 1
1,
#505
0,
#510
b110000 +
b110000 1
1,
#515
0,
#520
b110001 +
b110001 1
1,
#525
0,
#530
b110010 +
b110010 1
1,
#535
0,
#540
b110011 +
b110011 1
1,
#545
0,
#550
b110100 +
b110100 1
1,
#555
0,
#560
b110101 +
b110101 1
1,
#565
0,
#570
b110110 +
b110110 1
1,
#575
0,
#580
b110111 +
b110111 1
1,
#585
0,
#590
b111000 +
b111000 1
1,
#595
0,
#600
b111001 +
b111001 1
1,
#605
0,
#610
b111010 +
b111010 1
1,
#615
0,
#620
b111011 +
b111011 1
1,
#625
0,
#630
b111100 +
b111100 1
1,
#635
0,
#640
b111101 +
b111101 1
1,
#645
0,
#650
b111110 +
b111110 1
1,
#655
0,
#660
b111111 +
b111111 1
1,
#665
0,
#670
b1000000 +
b1000000 1
1,
#675
0,
#680
b1000001 +
b1000001 1
1,
#685
0,
#690
b1000010 +
b1000010 1
1,
#695
0,
#700
b1000011 +
b1000011 1
1,
#705
0,
#710
b1000100 +
b1000100 1
1,
#715
0,
#720
b1000101 +
b1000101 1
1,
#725
0,
#730
b1000110 +
b1000110 1
1,
#735
0,
#740
b1000111 +
b1000111 1
1,
#745
0,
#750
b1001000 +
b1001000 1
1,
#755
0,
#760
b1001001 +
b1001001 1
1,
#765
0,
#770
b1001010 +
b1001010 1
1,
#775
0,
#780
b1001011 +
b1001011 1
1,
#785
0,
#790
b1001100 +
b1001100 1
1,
#795
0,
#800
b1001101 +
b1001101 1
1,
#805
0,
#810
b1001110 +
b1001110 1
1,
#815
0,
#820
b1001111 +
b1001111 1
1,
#825
0,
#830
b1010000 +
b1010000 1
1,
#835
0,
#840
b1010001 +
b1010001 1
1,
#845
0,
#850
b1010010 +
b1010010 1
1,
#855
0,
#860
b1010011 +
b1010011 1
1,
#865
0,
#870
b1010100 +
b1010100 1
1,
#875
0,
#880
b1010101 +
b1010101 1
1,
#885
0,
#890
b1010110 +
b1010110 1
1,
#895
0,
#900
b1010111 +
b1010111 1
1,
#905
0,
#910
b1011000 +
b1011000 1
1,
#915
0,
#920
b1011001 +
b1011001 1
1,
#925
0,
#930
b1011010 +
b1011010 1
1,
#935
0,
#940
b1011011 +
b1011011 1
1,
#945
0,
#950
b1011100 +
b1011100 1
1,
#955
0,
#960
b1011101 +
b1011101 1
1,
#965
0,
#970
b1011110 +
b1011110 1
1,
#975
0,
#980
b1011111 +
b1011111 1
1,
#985
0,
#990
b1100000 +
b1100000 1
1,
#995
0,
#1000
b1100001 +
b1100001 1
1,
b10000000000 :
#1005
0,
#1010
b1100010 +
b1100010 1
1,
#1015
0,
#1020
b1100011 +
b1100011 1
1,
#1025
0,
#1030
b1100100 +
b1100100 1
1,
#1035
0,
#1040
b1100101 +
b1100101 1
1,
