rtl/Macs/PE.v
module PE (
    input                   clk,
    input                   rstn,
    input       [15:0]      A,
    input       [15:0]      B,
    input       [15:0]      C,
    input                   en,
    output  reg  [15:0]     result,
    output  reg             valid
);

    reg mode;

    always @(posedge clk or negedge rstn) begin
        if(!rstn)begin
            result <= 0;
            valid <= 0;
            mode <= 0;
        end
        // else if(en) begin
        //     if(!mode)begin
        //         result <= A * B;
        //         valid <= 0;
        //         mode <= 1;
        //     end
        //     else begin
        //         result <= result + C;
        //         valid <= 1;
        //         mode <= 0;
        //     end
        // end

        else if(!mode) begin
            if(en)begin
                result <= A*B;
                valid <= 0;
                mode <= 1;
            end
            else
                valid <= 0;
        end
        else begin
            result <= result + C;
            valid <= 1;
            mode <= 0;
        end


    end
endmodule

rtl/Macs/Macs.v
module  Macs(
    input               clk,
    input               rstn,
    input   [15:0]      A,
    input   [15:0]      B_0,
    input   [15:0]      B_1,
    input   [15:0]      B_2,
    input   [15:0]      B_3,
    input   [15:0]      C_0,
    input   [15:0]      C_1,
    input   [15:0]      C_2,
    input   [15:0]      C_3,
    input               en,
    input               mode,
    input               signal,
    output              valid,
    output  [15:0]      result_0,
    output  [15:0]      result_1,
    output  [15:0]      result_2,
    output  [15:0]      result_3
);

    localparam matmul = 1'b0;
    localparam matadd = 1'b1;


    wire [15:0]  A_temp;
    assign A_temp = mode==matadd ? 1 : (signal? (~A + 1'b1) : A );

    PE u_PE_0 (
        .clk(clk),
        .rstn(rstn),
        .A(A_temp),
        .B(B_0),
        .C(C_0),
        .en(en),
        .result(result_0),
        .valid(valid)
    );

    PE u_PE_1 (
        .clk(clk),
        .rstn(rstn),
        .A(A_temp),
        .B(B_1),
        .C(C_1),
        .en(en),
        .result(result_1)
    );

    PE u_PE_2 (
        .clk(clk),
        .rstn(rstn),
        .A(A_temp),
        .B(B_2),
        .C(C_2),
        .en(en),
        .result(result_2)
    );

    PE u_PE_3 (
        .clk(clk),
        .rstn(rstn),
        .A(A_temp),
        .B(B_3),
        .C(C_3),
        .en(en),
        .result(result_3)
    );

    
endmodule

sim/tb_Macs.v
`timescale 1ns / 1ns
`include "../rtl/Macs/Macs.v"
module tb_Macs;

// Testbench signals
reg clk;
reg rstn;
reg [15:0] A;
reg [15:0] B_0, B_1, B_2, B_3;
reg [15:0] C_0, C_1, C_2, C_3;
reg en;
reg mode;
reg signal;

wire valid;
wire [15:0] result_0, result_1, result_2, result_3;

// Instantiate the Macs module
Macs uut (
    .clk(clk),
    .rstn(rstn),
    .A(A),
    .B_0(B_0),
    .B_1(B_1),
    .B_2(B_2),
    .B_3(B_3),
    .C_0(C_0),
    .C_1(C_1),
    .C_2(C_2),
    .C_3(C_3),
    .en(en),
    .mode(mode),
    .signal(signal),
    .valid(valid),
    .result_0(result_0),
    .result_1(result_1),
    .result_2(result_2),
    .result_3(result_3)
);

// Clock generation
always begin
    #5 clk = ~clk;  // 100 MHz clock
end

// Initial block to drive inputs and check outputs
initial begin
    // Initialize signals
    $dumpfile("wave/Macs.vcd");
    $dumpvars(0, tb_Macs);
    clk = 0;
    rstn = 0;
    A = 16'b0;
    B_0 = 16'b0; B_1 = 16'b0; B_2 = 16'b0; B_3 = 16'b0;
    C_0 = 16'b0; C_1 = 16'b0; C_2 = 16'b0; C_3 = 16'b0;
    en = 0;
    mode = 0;
    signal = 0;

    // Apply reset
    #10;
    rstn = 1;

    // Test 1: Multiply mode (matmul) with signal = 0
    A = 16'h3;  // A = 3
    B_0 = 16'h2; B_1 = 16'h4; B_2 = 16'h1; B_3 = 16'h5;
    C_0 = 16'h0; C_1 = 16'h0; C_2 = 16'h0; C_3 = 16'h0;
    en = 1;
    mode = 0;  // matmul mode
    signal = 0;  // normal multiplication
    #20;

    A = 16'h1;  // A = 3
    B_0 = 16'h3; B_1 = 16'h4; B_2 = 16'h1; B_3 = 16'h5;
    C_0 = 16'h4; C_1 = 16'h0; C_2 = 16'h0; C_3 = 16'h0;
    en = 1;
    mode = 0;  // matmul mode
    signal = 0;  // normal multiplication
    #20;

    A = 16'h3;  // A = 3
    B_0 = 16'h4; B_1 = 16'h4; B_2 = 16'h1; B_3 = 16'h5;
    C_0 = 16'h5; C_1 = 16'h0; C_2 = 16'h0; C_3 = 16'h0;
    en = 1;
    mode = 0;  // matmul mode
    signal = 0;  // normal multiplication
    #40;

    A = 16'h3;  // A = 3
    B_0 = 16'h3; B_1 = 16'h4; B_2 = 16'h1; B_3 = 16'h5;
    C_0 = 16'h3; C_1 = 16'h0; C_2 = 16'h0; C_3 = 16'h0;
    en = 1;
    mode = 0;  // matmul mode
    signal = 0;  // normal multiplication
    #20;

    // Test 2: Add mode (matadd)
    A = 16'h3;  // A = 3
    B_0 = 16'h2; B_1 = 16'h4; B_2 = 16'h1; B_3 = 16'h5;
    C_0 = 16'h6; C_1 = 16'h6; C_2 = 16'h6; C_3 = 16'h6;
    mode = 1;  // matadd mode
    signal = 0;  // normal addition
    #20;

    A = 16'h5;  // A = 3
    B_0 = 16'h1; B_1 = 16'h4; B_2 = 16'h1; B_3 = 16'h5;
    C_0 = 16'h7; C_1 = 16'h6; C_2 = 16'h6; C_3 = 16'h6;
    mode = 1;  // matadd mode
    signal = 0;  // normal addition
    #20;

    A = 16'h2;  // A = 3
    B_0 = 16'h3; B_1 = 16'h4; B_2 = 16'h1; B_3 = 16'h5;
    C_0 = 16'h4; C_1 = 16'h6; C_2 = 16'h6; C_3 = 16'h6;
    mode = 1;  // matadd mode
    signal = 0;  // normal addition
    #40;

    A = 16'h6;  // A = 3
    B_0 = 16'h2; B_1 = 16'h4; B_2 = 16'h1; B_3 = 16'h5;
    C_0 = 16'h1; C_1 = 16'h6; C_2 = 16'h6; C_3 = 16'h6;
    mode = 1;  // matadd mode
    signal = 0;  // normal addition
    #20;

    // Test 3: Matmul with negative A (signal = 1)
    A = 16'h1;  // A = 3
    B_0 = 16'h3; B_1 = 16'h4; B_2 = 16'h1; B_3 = 16'h5;
    C_0 = 16'h2; C_1 = 16'h6; C_2 = 16'h6; C_3 = 16'h6;
    mode = 0;  // matadd mode
    signal = 1;  // normal addition
    #20;

    A = 16'h3;  // A = 3
    B_0 = 16'h5; B_1 = 16'h4; B_2 = 16'h1; B_3 = 16'h5;
    C_0 = 16'h2; C_1 = 16'h6; C_2 = 16'h6; C_3 = 16'h6;
    mode = 0;  // matadd mode
    signal = 1;  // normal addition
    #20;

    A = 16'h1;  // A = 3
    B_0 = 16'h2; B_1 = 16'h4; B_2 = 16'h1; B_3 = 16'h5;
    C_0 = 16'h2; C_1 = 16'h6; C_2 = 16'h6; C_3 = 16'h6;
    mode = 0;  // matadd mode
    signal = 1;  // normal addition
    #40;

    A = 16'h3;  // A = 3
    B_0 = 16'h3; B_1 = 16'h4; B_2 = 16'h1; B_3 = 16'h5;
    C_0 = 16'h3; C_1 = 16'h6; C_2 = 16'h6; C_3 = 16'h6;
    mode = 0;  // matadd mode
    signal = 1;  // normal addition
    #20;

    // Test 4: Enable pulse for en = 0 and 1 for further test case transitions
    en = 0;
    #10;
    en = 1;
    #10;

    // Test 5: Changing inputs while keeping mode to matadd
    A = 16'h8;
    B_0 = 16'h1; B_1 = 16'h2; B_2 = 16'h3; B_3 = 16'h4;
    C_0 = 16'h7; C_1 = 16'h8; C_2 = 16'h9; C_3 = 16'hA;
    #40;

    // End the simulation
    $finish;
end

// Monitor outputs
// initial begin
//     $monitor("Time=%0t | A=%d | B_0=%d B_1=%d B_2=%d B_3=%d | C_0=%d C_1=%d C_2=%d C_3=%d | Mode=%b | Result: %d %d %d %d | Valid=%b", 
//              $time, A, B_0, B_1, B_2, B_3, C_0, C_1, C_2, C_3, mode, result_0, result_1, result_2, result_3, valid);
// end

endmodule

sim/wave/Macs.vcd
$date
	Wed Dec 11 15:02:37 2024
$end
$version
	Icarus Verilog
$end
$timescale
	1ns
$end
$scope module tb_Macs $end
$var wire 1 ! valid $end
$var wire 16 " result_3 [15:0] $end
$var wire 16 # result_2 [15:0] $end
$var wire 16 $ result_1 [15:0] $end
$var wire 16 % result_0 [15:0] $end
$var reg 16 & A [15:0] $end
$var reg 16 ' B_0 [15:0] $end
$var reg 16 ( B_1 [15:0] $end
$var reg 16 ) B_2 [15:0] $end
$var reg 16 * B_3 [15:0] $end
$var reg 16 + C_0 [15:0] $end
$var reg 16 , C_1 [15:0] $end
$var reg 16 - C_2 [15:0] $end
$var reg 16 . C_3 [15:0] $end
$var reg 1 / clk $end
$var reg 1 0 en $end
$var reg 1 1 mode $end
$var reg 1 2 rstn $end
$var reg 1 3 signal $end
$scope module uut $end
$var wire 16 4 A [15:0] $end
$var wire 16 5 B_0 [15:0] $end
$var wire 16 6 B_1 [15:0] $end
$var wire 16 7 B_2 [15:0] $end
$var wire 16 8 B_3 [15:0] $end
$var wire 16 9 C_0 [15:0] $end
$var wire 16 : C_1 [15:0] $end
$var wire 16 ; C_2 [15:0] $end
$var wire 16 < C_3 [15:0] $end
$var wire 1 / clk $end
$var wire 1 0 en $end
$var wire 1 1 mode $end
$var wire 1 2 rstn $end
$var wire 1 3 signal $end
$var wire 1 ! valid $end
$var wire 16 = result_3 [15:0] $end
$var wire 16 > result_2 [15:0] $end
$var wire 16 ? result_1 [15:0] $end
$var wire 16 @ result_0 [15:0] $end
$var wire 16 A A_temp [15:0] $end
$var parameter 1 B matadd $end
$var parameter 1 C matmul $end
$scope module u_PE_0 $end
$var wire 16 D A [15:0] $end
$var wire 16 E B [15:0] $end
$var wire 16 F C [15:0] $end
$var wire 1 / clk $end
$var wire 1 0 en $end
$var wire 1 2 rstn $end
$var reg 1 G mode $end
$var reg 16 H result [15:0] $end
$var reg 1 ! valid $end
$upscope $end
$scope module u_PE_1 $end
$var wire 16 I A [15:0] $end
$var wire 16 J B [15:0] $end
$var wire 16 K C [15:0] $end
$var wire 1 / clk $end
$var wire 1 0 en $end
$var wire 1 2 rstn $end
$var reg 1 L mode $end
$var reg 16 M result [15:0] $end
$var reg 1 N valid $end
$upscope $end
$scope module u_PE_2 $end
$var wire 16 O A [15:0] $end
$var wire 16 P B [15:0] $end
$var wire 16 Q C [15:0] $end
$var wire 1 / clk $end
$var wire 1 0 en $end
$var wire 1 2 rstn $end
$var reg 1 R mode $end
$var reg 16 S result [15:0] $end
$var reg 1 T valid $end
$upscope $end
$scope module u_PE_3 $end
$var wire 16 U A [15:0] $end
$var wire 16 V B [15:0] $end
$var wire 16 W C [15:0] $end
$var wire 1 / clk $end
$var wire 1 0 en $end
$var wire 1 2 rstn $end
$var reg 1 X mode $end
$var reg 16 Y result [15:0] $end
$var reg 1 Z valid $end
$upscope $end
$upscope $end
$upscope $end
$enddefinitions $end
$comment Show the parameter values. $end
$dumpall
0C
1B
$end
#0
$dumpvars
0Z
b0 Y
0X
b0 W
b0 V
b0 U
0T
b0 S
0R
b0 Q
b0 P
b0 O
0N
b0 M
0L
b0 K
b0 J
b0 I
b0 H
0G
b0 F
b0 E
b0 D
b0 A
b0 @
b0 ?
b0 >
b0 =
b0 <
b0 ;
b0 :
b0 9
b0 8
b0 7
b0 6
b0 5
b0 4
03
02
01
00
0/
b0 .
b0 -
b0 ,
b0 +
b0 *
b0 )
b0 (
b0 '
b0 &
b0 %
b0 $
b0 #
b0 "
0!
$end
#5
1/
#10
b11 A
b11 D
b11 I
b11 O
b11 U
0/
10
b101 *
b101 8
b101 V
b1 )
b1 7
b1 P
b100 (
b100 6
b100 J
b10 '
b10 5
b10 E
b11 &
b11 4
12
#15
1G
b110 %
b110 @
b110 H
1L
b1100 $
b1100 ?
b1100 M
1R
b11 #
b11 >
b11 S
1X
b1111 "
b1111 =
b1111 Y
1/
#20
0/
#25
1Z
0X
1T
0R
1N
0L
1!
0G
1/
#30
b1 A
b1 D
b1 I
b1 O
b1 U
0/
b100 +
b100 9
b100 F
b11 '
b11 5
b11 E
b1 &
b1 4
#35
1G
0!
b11 %
b11 @
b11 H
1L
0N
b100 $
b100 ?
b100 M
1R
0T
b1 #
b1 >
b1 S
1X
0Z
b101 "
b101 =
b101 Y
1/
#40
0/
#45
1Z
0X
1T
0R
1N
0L
1!
b111 %
b111 @
b111 H
0G
1/
#50
b11 A
b11 D
b11 I
b11 O
b11 U
0/
b101 +
b101 9
b101 F
b100 '
b100 5
b100 E
b11 &
b11 4
#55
1G
0!
b1100 %
b1100 @
b1100 H
1L
0N
b1100 $
b1100 ?
b1100 M
1R
0T
b11 #
b11 >
b11 S
1X
0Z
b1111 "
b1111 =
b1111 Y
1/
#60
0/
#65
1Z
0X
1T
0R
1N
0L
1!
b10001 %
b10001 @
b10001 H
0G
1/
#70
0/
#75
1G
0!
b1100 %
b1100 @
b1100 H
1L
0N
1R
0T
1X
0Z
1/
#80
0/
#85
1Z
0X
1T
0R
1N
0L
1!
b10001 %
b10001 @
b10001 H
0G
1/
#90
0/
b11 +
b11 9
b11 F
b11 '
b11 5
b11 E
#95
1G
0!
b1001 %
b1001 @
b1001 H
1L
0N
1R
0T
1X
0Z
1/
#100
0/
#105
1Z
0X
1T
0R
1N
0L
1!
b1100 %
b1100 @
b1100 H
0G
1/
#110
b1 A
b1 D
b1 I
b1 O
b1 U
0/
11
b110 .
b110 <
b110 W
b110 -
b110 ;
b110 Q
b110 ,
b110 :
b110 K
b110 +
b110 9
b110 F
b10 '
b10 5
b10 E
#115
1G
0!
b10 %
b10 @
b10 H
1L
0N
b100 $
b100 ?
b100 M
1R
0T
b1 #
b1 >
b1 S
1X
0Z
b101 "
b101 =
b101 Y
1/
#120
0/
#125
1Z
b1011 "
b1011 =
b1011 Y
0X
1T
b111 #
b111 >
b111 S
0R
1N
b1010 $
b1010 ?
b1010 M
0L
1!
b1000 %
b1000 @
b1000 H
0G
1/
#130
0/
b111 +
b111 9
b111 F
b1 '
b1 5
b1 E
b101 &
b101 4
#135
1G
0!
b1 %
b1 @
b1 H
1L
0N
b100 $
b100 ?
b100 M
1R
0T
b1 #
b1 >
b1 S
1X
0Z
b101 "
b101 =
b101 Y
1/
#140
0/
#145
1Z
b1011 "
b1011 =
b1011 Y
0X
1T
b111 #
b111 >
b111 S
0R
1N
b1010 $
b1010 ?
b1010 M
0L
1!
b1000 %
b1000 @
b1000 H
0G
1/
#150
0/
b100 +
b100 9
b100 F
b11 '
b11 5
b11 E
b10 &
b10 4
#155
1G
0!
b11 %
b11 @
b11 H
1L
0N
b100 $
b100 ?
b100 M
1R
0T
b1 #
b1 >
b1 S
1X
0Z
b101 "
b101 =
b101 Y
1/
#160
0/
#165
1Z
b1011 "
b1011 =
b1011 Y
0X
1T
b111 #
b111 >
b111 S
0R
1N
b1010 $
b1010 ?
b1010 M
0L
1!
b111 %
b111 @
b111 H
0G
1/
#170
0/
#175
1G
0!
b11 %
b11 @
b11 H
1L
0N
b100 $
b100 ?
b100 M
1R
0T
b1 #
b1 >
b1 S
1X
0Z
b101 "
b101 =
b101 Y
1/
#180
0/
#185
1Z
b1011 "
b1011 =
b1011 Y
0X
1T
b111 #
b111 >
b111 S
0R
1N
b1010 $
b1010 ?
b1010 M
0L
1!
b111 %
b111 @
b111 H
0G
1/
#190
0/
b1 +
b1 9
b1 F
b10 '
b10 5
b10 E
b110 &
b110 4
#195
1G
0!
b10 %
b10 @
b10 H
1L
0N
b100 $
b100 ?
b100 M
1R
0T
b1 #
b1 >
b1 S
1X
0Z
b101 "
b101 =
b101 Y
1/
#200
0/
#205
1Z
b1011 "
b1011 =
b1011 Y
0X
1T
b111 #
b111 >
b111 S
0R
1N
b1010 $
b1010 ?
b1010 M
0L
1!
b11 %
b11 @
b11 H
0G
1/
#210
b1111111111111111 A
b1111111111111111 D
b1111111111111111 I
b1111111111111111 O
b1111111111111111 U
0/
13
01
b10 +
b10 9
b10 F
b11 '
b11 5
b11 E
b1 &
b1 4
#215
1G
0!
b1111111111111101 %
b1111111111111101 @
b1111111111111101 H
1L
0N
b1111111111111100 $
b1111111111111100 ?
b1111111111111100 M
1R
0T
b1111111111111111 #
b1111111111111111 >
b1111111111111111 S
1X
0Z
b1111111111111011 "
b1111111111111011 =
b1111111111111011 Y
1/
#220
0/
#225
1Z
b1 "
b1 =
b1 Y
0X
1T
b101 #
b101 >
b101 S
0R
1N
b10 $
b10 ?
b10 M
0L
1!
b1111111111111111 %
b1111111111111111 @
b1111111111111111 H
0G
1/
#230
b1111111111111101 A
b1111111111111101 D
b1111111111111101 I
b1111111111111101 O
b1111111111111101 U
0/
b101 '
b101 5
b101 E
b11 &
b11 4
#235
1G
0!
b1111111111110001 %
b1111111111110001 @
b1111111111110001 H
1L
0N
b1111111111110100 $
b1111111111110100 ?
b1111111111110100 M
1R
0T
b1111111111111101 #
b1111111111111101 >
b1111111111111101 S
1X
0Z
b1111111111110001 "
b1111111111110001 =
b1111111111110001 Y
1/
#240
0/
#245
1Z
b1111111111110111 "
b1111111111110111 =
b1111111111110111 Y
0X
1T
b11 #
b11 >
b11 S
0R
1N
b1111111111111010 $
b1111111111111010 ?
b1111111111111010 M
0L
1!
b1111111111110011 %
b1111111111110011 @
b1111111111110011 H
0G
1/
#250
b1111111111111111 A
b1111111111111111 D
b1111111111111111 I
b1111111111111111 O
b1111111111111111 U
0/
b10 '
b10 5
b10 E
b1 &
b1 4
#255
1G
0!
b1111111111111110 %
b1111111111111110 @
b1111111111111110 H
1L
0N
b1111111111111100 $
b1111111111111100 ?
b1111111111111100 M
1R
0T
b1111111111111111 #
b1111111111111111 >
b1111111111111111 S
1X
0Z
b1111111111111011 "
b1111111111111011 =
b1111111111111011 Y
1/
#260
0/
#265
1Z
b1 "
b1 =
b1 Y
0X
1T
b101 #
b101 >
b101 S
0R
1N
b10 $
b10 ?
b10 M
0L
1!
b0 %
b0 @
b0 H
0G
1/
#270
0/
#275
1G
0!
b1111111111111110 %
b1111111111111110 @
b1111111111111110 H
1L
0N
b1111111111111100 $
b1111111111111100 ?
b1111111111111100 M
1R
0T
b1111111111111111 #
b1111111111111111 >
b1111111111111111 S
1X
0Z
b1111111111111011 "
b1111111111111011 =
b1111111111111011 Y
1/
#280
0/
#285
1Z
b1 "
b1 =
b1 Y
0X
1T
b101 #
b101 >
b101 S
0R
1N
b10 $
b10 ?
b10 M
0L
1!
b0 %
b0 @
b0 H
0G
1/
#290
b1111111111111101 A
b1111111111111101 D
b1111111111111101 I
b1111111111111101 O
b1111111111111101 U
0/
b11 +
b11 9
b11 F
b11 '
b11 5
b11 E
b11 &
b11 4
#295
1G
0!
b1111111111110111 %
b1111111111110111 @
b1111111111110111 H
1L
0N
b1111111111110100 $
b1111111111110100 ?
b1111111111110100 M
1R
0T
b1111111111111101 #
b1111111111111101 >
b1111111111111101 S
1X
0Z
b1111111111110001 "
b1111111111110001 =
b1111111111110001 Y
1/
#300
0/
#305
1Z
b1111111111110111 "
b1111111111110111 =
b1111111111110111 Y
0X
1T
b11 #
b11 >
b11 S
0R
1N
b1111111111111010 $
b1111111111111010 ?
b1111111111111010 M
0L
1!
b1111111111111010 %
b1111111111111010 @
b1111111111111010 H
0G
1/
#310
0/
00
#315
1/
#320
0/
10
#325
0Z
b1111111111110001 "
b1111111111110001 =
b1111111111110001 Y
1X
0T
b1111111111111101 #
b1111111111111101 >
b1111111111111101 S
1R
0N
b1111111111110100 $
b1111111111110100 ?
b1111111111110100 M
1L
0!
b1111111111110111 %
b1111111111110111 @
b1111111111110111 H
1G
1/
#330
b1111111111111000 A
b1111111111111000 D
b1111111111111000 I
b1111111111111000 O
b1111111111111000 U
0/
b1010 .
b1010 <
b1010 W
b1001 -
b1001 ;
b1001 Q
b1000 ,
b1000 :
b1000 K
b111 +
b111 9
b111 F
b100 *
b100 8
b100 V
b11 )
b11 7
b11 P
b10 (
b10 6
b10 J
b1 '
b1 5
b1 E
b1000 &
b1000 4
#335
0G
1!
b1111111111111110 %
b1111111111111110 @
b1111111111111110 H
0L
1N
b1111111111111100 $
b1111111111111100 ?
b1111111111111100 M
0R
1T
b110 #
b110 >
b110 S
0X
1Z
b1111111111111011 "
b1111111111111011 =
b1111111111111011 Y
1/
#340
0/
#345
0Z
b1111111111100000 "
b1111111111100000 =
b1111111111100000 Y
1X
0T
b1111111111101000 #
b1111111111101000 >
b1111111111101000 S
1R
0N
b1111111111110000 $
b1111111111110000 ?
b1111111111110000 M
1L
0!
b1111111111111000 %
b1111111111111000 @
b1111111111111000 H
1G
1/
#350
0/
#355
0G
1!
b1111111111111111 %
b1111111111111111 @
b1111111111111111 H
0L
1N
b1111111111111000 $
b1111111111111000 ?
b1111111111111000 M
0R
1T
b1111111111110001 #
b1111111111110001 >
b1111111111110001 S
0X
1Z
b1111111111101010 "
b1111111111101010 =
b1111111111101010 Y
1/
#360
0/
#365
0Z
b1111111111100000 "
b1111111111100000 =
b1111111111100000 Y
1X
0T
b1111111111101000 #
b1111111111101000 >
b1111111111101000 S
1R
0N
b1111111111110000 $
b1111111111110000 ?
b1111111111110000 M
1L
0!
b1111111111111000 %
b1111111111111000 @
b1111111111111000 H
1G
1/
